tm4j_reporter_robot/TM4JCycleDescriptor.py
tm4j_reporter_robot/TM4JRobotListener.py
tm4j_reporter_robot/__init__.py
tm4j_reporter_robot/library_variables.py
tm4j_reporter_robot/tm4j_robot_helpers/__init__.py
tm4j_reporter_robot/tm4j_robot_helpers/tm4j_config_helpers.py
tm4j_reporter_robot/tm4j_robot_helpers/tm4j_test_cycle_helpers.py
tm4j_reporter_robot-0.1.4.dist-info/LICENSE
tm4j_reporter_robot-0.1.4.dist-info/METADATA
tm4j_reporter_robot-0.1.4.dist-info/WHEEL
tm4j_reporter_robot-0.1.4.dist-info/top_level.txt
tm4j_reporter_robot-0.1.4.dist-info/RECORD
