Metadata-Version: 2.1
Name: tm4j-reporter-robot
Version: 0.1.4
Summary: python package providing Robot Framework integration with Jira Test Management (tm4j) Cloud
Home-page: https://github.com/Klika-Tech/tm4j_reporter_robot
Author: Klika-Tech, Inc
Author-email: contact@klika-tech.com
License: MIT
Keywords: python tm4j jira test testmanagement report robotframework
Platform: any
Classifier: Intended Audience :: Developers
Classifier: License :: OSI Approved :: MIT License
Classifier: Operating System :: OS Independent
Classifier: Programming Language :: Python
Classifier: Programming Language :: Python :: 3
Classifier: Topic :: Software Development :: Quality Assurance
Classifier: Topic :: Software Development :: Testing
Classifier: Topic :: Utilities
Classifier: Topic :: Software Development :: Libraries :: Python Modules
Requires-Python: >=3.6
Requires-Dist: filelock
Requires-Dist: tm4j-reporter-api
